pwpy/__init__.py
pwpy/api.py
pwpy/exceptions.py
pwpy/queries.py
pwpy/scrape.py
pwpy/urls.py
pwpy/utils.py
tests/__init__.py
tests/test_api.py
tests/test_scrape.py
tests/test_utils.py
pwpy-0.6.0.dist-info/LICENSE
pwpy-0.6.0.dist-info/METADATA
pwpy-0.6.0.dist-info/WHEEL
pwpy-0.6.0.dist-info/top_level.txt
pwpy-0.6.0.dist-info/RECORD
